srtranslator/__init__.py
srtranslator/__main__.py
srtranslator/ass_file.py
srtranslator/srt_file.py
srtranslator/util.py
srtranslator/translators/__init__.py
srtranslator/translators/base.py
srtranslator/translators/deepl_api.py
srtranslator/translators/deepl_scrap.py
srtranslator/translators/pydeeplx.py
srtranslator/translators/selenium_utils.py
srtranslator/translators/translatepy.py
srtranslator-0.3.9.dist-info/LICENSE.md
srtranslator-0.3.9.dist-info/METADATA
srtranslator-0.3.9.dist-info/WHEEL
srtranslator-0.3.9.dist-info/top_level.txt
srtranslator-0.3.9.dist-info/RECORD
