Metadata-Version: 2.1
Name: srtranslator
Version: 0.3.9
Summary: Traslate a .SRT file using any custom translator
Home-page: https://github.com/sinedie/SRTranslator
Author: EAR
Author-email: sinedie@protonmail.com
License: FREE
Keywords: python,srt,languages,translator,subtitles
Requires-Python: >=3.6
License-File: LICENSE.md
Requires-Dist: deepl ==1.19.1
Requires-Dist: free-proxy ==1.1.2
Requires-Dist: pyass ==0.1.4
Requires-Dist: translatepy ==2.3
Requires-Dist: selenium ==4.7.2
Requires-Dist: srt ==3.5.3
Requires-Dist: PyDeepLX ==1.0.7
Requires-Dist: webdriverdownloader ==1.1.0.4
